exodide/__init__.py
exodide/build.py
exodide/exodide_wheel.py
exodide/inspect.py
exodide/install.py
exodide/cpython/LICENSE
exodide/cpython/Python.h
exodide/cpython/abstract.h
exodide/cpython/bltinmodule.h
exodide/cpython/boolobject.h
exodide/cpython/bytearrayobject.h
exodide/cpython/bytesobject.h
exodide/cpython/cellobject.h
exodide/cpython/ceval.h
exodide/cpython/classobject.h
exodide/cpython/code.h
exodide/cpython/codecs.h
exodide/cpython/compile.h
exodide/cpython/complexobject.h
exodide/cpython/context.h
exodide/cpython/datetime.h
exodide/cpython/descrobject.h
exodide/cpython/dictobject.h
exodide/cpython/dynamic_annotations.h
exodide/cpython/enumobject.h
exodide/cpython/errcode.h
exodide/cpython/eval.h
exodide/cpython/exports.h
exodide/cpython/fileobject.h
exodide/cpython/fileutils.h
exodide/cpython/floatobject.h
exodide/cpython/frameobject.h
exodide/cpython/funcobject.h
exodide/cpython/genericaliasobject.h
exodide/cpython/genobject.h
exodide/cpython/import.h
exodide/cpython/interpreteridobject.h
exodide/cpython/intrcheck.h
exodide/cpython/iterobject.h
exodide/cpython/listobject.h
exodide/cpython/longintrepr.h
exodide/cpython/longobject.h
exodide/cpython/marshal.h
exodide/cpython/memoryobject.h
exodide/cpython/methodobject.h
exodide/cpython/modsupport.h
exodide/cpython/moduleobject.h
exodide/cpython/namespaceobject.h
exodide/cpython/object.h
exodide/cpython/objimpl.h
exodide/cpython/opcode.h
exodide/cpython/osdefs.h
exodide/cpython/osmodule.h
exodide/cpython/patchlevel.h
exodide/cpython/py_curses.h
exodide/cpython/pycapsule.h
exodide/cpython/pyconfig.h
exodide/cpython/pydtrace.h
exodide/cpython/pyerrors.h
exodide/cpython/pyexpat.h
exodide/cpython/pyframe.h
exodide/cpython/pyhash.h
exodide/cpython/pylifecycle.h
exodide/cpython/pymacconfig.h
exodide/cpython/pymacro.h
exodide/cpython/pymath.h
exodide/cpython/pymem.h
exodide/cpython/pyport.h
exodide/cpython/pystate.h
exodide/cpython/pystrcmp.h
exodide/cpython/pystrhex.h
exodide/cpython/pystrtod.h
exodide-1.0.4.dist-info/LICENSE
exodide-1.0.4.dist-info/METADATA
exodide-1.0.4.dist-info/WHEEL
exodide-1.0.4.dist-info/top_level.txt
exodide-1.0.4.dist-info/RECORD
