Metadata-Version: 2.1
Name: exodide
Version: 1.0.4
Summary: build_ext for Pyodide
Home-page: https://github.com/ymd-h/exodide
Author: Yamada Hiroyuki
License: UNKNOWN
Platform: UNKNOWN
Classifier: Programming Language :: Python
Classifier: Programming Language :: Python :: 3
Classifier: Development Status :: 4 - Beta
Classifier: Operating System :: OS Independent
Classifier: Intended Audience :: Developers
Classifier: Topic :: Software Development :: Libraries
License-File: LICENSE
Requires-Dist: well-behaved-logging
Provides-Extra: all
Requires-Dist: wheel ; extra == 'all'
Requires-Dist: numpy ; extra == 'all'
Provides-Extra: build
Requires-Dist: wheel ; extra == 'build'
Provides-Extra: inspect
Requires-Dist: numpy ; extra == 'inspect'
